[{"arm_l":4,"arm_r":4,"body":4,"comp":3,"id":0,"legs":4,"pack":1,"pilot":5,"pod_l":1,"pod_r":1,"wpn_l":3,"wpn_r":3},{"arm_l":4,"arm_r":4,"body":4,"comp":1,"id":1,"legs":4,"pack":4,"pilot":10,"pod_l":1,"pod_r":1,"wpn_l":7,"wpn_r":7},{"arm_l":3,"arm_r":3,"body":3,"comp":2,"id":2,"legs":3,"pack":1,"pilot":37,"pod_l":3,"pod_r":3,"wpn_l":6,"wpn_r":6},{"arm_l":2,"arm_r":2,"body":2,"comp":2,"id":3,"legs":2,"pack":1,"pilot":4,"pod_l":5,"pod_r":5,"wpn_l":7,"wpn_r":7},{"arm_l":5,"arm_r":5,"body":5,"comp":2,"id":4,"legs":5,"pack":3,"pilot":62,"pod_l":1,"pod_r":1,"wpn_l":2,"wpn_r":2},{"arm_l":1,"arm_r":1,"body":1,"comp":5,"id":5,"legs":1,"pack":3,"pilot":38,"pod_l":4,"pod_r":4,"wpn_l":2,"wpn_r":2},{"arm_l":2,"arm_r":2,"body":2,"comp":4,"id":6,"legs":2,"pack":3,"pilot":39,"pod_l":5,"pod_r":5,"wpn_l":8,"wpn_r":8},{"arm_l":3,"arm_r":3,"body":3,"comp":3,"id":7,"legs":3,"pack":2,"pilot":42,"pod_l":1,"pod_r":1,"wpn_l":4,"wpn_r":4},{"arm_l":2,"arm_r":2,"body":2,"comp":4,"id":8,"legs":2,"pack":4,"pilot":17,"pod_l":1,"pod_r":1,"wpn_l":6,"wpn_r":6},{"arm_l":1,"arm_r":1,"body":1,"comp":4,"id":9,"legs":1,"pack":5,"pilot":20,"pod_l":2,"pod_r":2,"wpn_l":6,"wpn_r":6},{"arm_l":1,"arm_r":1,"body":1,"comp":2,"id":10,"legs":1,"pack":5,"pilot":15,"pod_l":1,"pod_r":1,"wpn_l":4,"wpn_r":4},{"arm_l":4,"arm_r":4,"body":4,"comp":5,"id":11,"legs":4,"pack":3,"pilot":32,"pod_l":2,"pod_r":2,"wpn_l":2,"wpn_r":2},{"arm_l":5,"arm_r":5,"body":5,"comp":3,"id":12,"legs":5,"pack":4,"pilot":29,"pod_l":2,"pod_r":2,"wpn_l":4,"wpn_r":4},{"arm_l":2,"arm_r":2,"body":2,"comp":5,"id":13,"legs":2,"pack":5,"pilot":30,"pod_l":3,"pod_r":3,"wpn_l":6,"wpn_r":6},{"arm_l":5,"arm_r":5,"body":5,"comp":4,"id":14,"legs":5,"pack":5,"pilot":57,"pod_l":3,"pod_r":3,"wpn_l":2,"wpn_r":2},{"arm_l":1,"arm_r":1,"body":1,"comp":3,"id":15,"legs":1,"pack":3,"pilot":12,"pod_l":3,"pod_r":3,"wpn_l":3,"wpn_r":3},{"arm_l":5,"arm_r":5,"body":5,"comp":3,"id":16,"legs":5,"pack":4,"pilot":2,"pod_l":2,"pod_r":2,"wpn_l":4,"wpn_r":4},{"arm_l":2,"arm_r":2,"body":2,"comp":1,"id":17,"legs":2,"pack":5,"pilot":60,"pod_l":1,"pod_r":1,"wpn_l":5,"wpn_r":5},{"arm_l":1,"arm_r":1,"body":1,"comp":1,"id":18,"legs":1,"pack":4,"pilot":9,"pod_l":3,"pod_r":3,"wpn_l":5,"wpn_r":5},{"arm_l":3,"arm_r":3,"body":3,"comp":3,"id":19,"legs":3,"pack":4,"pilot":11,"pod_l":4,"pod_r":4,"wpn_l":2,"wpn_r":2},{"arm_l":3,"arm_r":3,"body":3,"comp":2,"id":20,"legs":3,"pack":4,"pilot":41,"pod_l":2,"pod_r":2,"wpn_l":8,"wpn_r":8},{"arm_l":4,"arm_r":4,"body":4,"comp":1,"id":21,"legs":4,"pack":3,"pilot":63,"pod_l":4,"pod_r":4,"wpn_l":7,"wpn_r":7},{"arm_l":3,"arm_r":3,"body":3,"comp":4,"id":22,"legs":3,"pack":3,"pilot":21,"pod_l":1,"pod_r":1,"wpn_l":1,"wpn_r":1},{"arm_l":1,"arm_r":1,"body":1,"comp":3,"id":23,"legs":1,"pack":5,"pilot":61,"pod_l":3,"pod_r":3,"wpn_l":6,"wpn_r":6},{"arm_l":2,"arm_r":2,"body":2,"comp":2,"id":24,"legs":2,"pack":5,"pilot":1,"pod_l":4,"pod_r":4,"wpn_l":3,"wpn_r":3},{"arm_l":4,"arm_r":4,"body":4,"comp":1,"id":25,"legs":4,"pack":4,"pilot":7,"pod_l":2,"pod_r":2,"wpn_l":6,"wpn_r":6},{"arm_l":4,"arm_r":4,"body":4,"comp":4,"id":26,"legs":4,"pack":3,"pilot":25,"pod_l":5,"pod_r":5,"wpn_l":4,"wpn_r":4},{"arm_l":2,"arm_r":2,"body":2,"comp":3,"id":27,"legs":2,"pack":3,"pilot":6,"pod_l":3,"pod_r":3,"wpn_l":2,"wpn_r":2},{"arm_l":1,"arm_r":1,"body":1,"comp":2,"id":28,"legs":1,"pack":2,"pilot":59,"pod_l":3,"pod_r":3,"wpn_l":4,"wpn_r":4},{"arm_l":2,"arm_r":2,"body":2,"comp":2,"id":29,"legs":2,"pack":5,"pilot":45,"pod_l":4,"pod_r":4,"wpn_l":4,"wpn_r":4},{"arm_l":5,"arm_r":5,"body":5,"comp":5,"id":30,"legs":5,"pack":5,"pilot":53,"pod_l":1,"pod_r":1,"wpn_l":3,"wpn_r":3},{"arm_l":1,"arm_r":1,"body":1,"comp":2,"id":31,"legs":1,"pack":5,"pilot":28,"pod_l":1,"pod_r":1,"wpn_l":5,"wpn_r":5},{"arm_l":2,"arm_r":2,"body":2,"comp":2,"id":32,"legs":2,"pack":4,"pilot":18,"pod_l":2,"pod_r":2,"wpn_l":2,"wpn_r":2},{"arm_l":2,"arm_r":2,"body":2,"comp":4,"id":33,"legs":2,"pack":5,"pilot":5,"pod_l":3,"pod_r":3,"wpn_l":7,"wpn_r":7},{"arm_l":5,"arm_r":5,"body":5,"comp":2,"id":34,"legs":5,"pack":2,"pilot":23,"pod_l":3,"pod_r":3,"wpn_l":6,"wpn_r":6},{"arm_l":5,"arm_r":5,"body":5,"comp":5,"id":35,"legs":5,"pack":3,"pilot":32,"pod_l":2,"pod_r":2,"wpn_l":8,"wpn_r":8},{"arm_l":1,"arm_r":1,"body":1,"comp":4,"id":36,"legs":1,"pack":2,"pilot":40,"pod_l":2,"pod_r":2,"wpn_l":5,"wpn_r":5},{"arm_l":2,"arm_r":2,"body":2,"comp":3,"id":37,"legs":2,"pack":3,"pilot":47,"pod_l":3,"pod_r":3,"wpn_l":2,"wpn_r":2},{"arm_l":2,"arm_r":2,"body":2,"comp":5,"id":38,"legs":2,"pack":2,"pilot":31,"pod_l":4,"pod_r":4,"wpn_l":6,"wpn_r":6},{"arm_l":2,"arm_r":2,"body":2,"comp":4,"id":39,"legs":2,"pack":4,"pilot":49,"pod_l":5,"pod_r":5,"wpn_l":7,"wpn_r":7},{"arm_l":3,"arm_r":3,"body":3,"comp":5,"id":40,"legs":3,"pack":1,"pilot":9,"pod_l":4,"pod_r":4,"wpn_l":2,"wpn_r":2},{"arm_l":4,"arm_r":4,"body":4,"comp":4,"id":41,"legs":4,"pack":3,"pilot":22,"pod_l":4,"pod_r":4,"wpn_l":3,"wpn_r":3},{"arm_l":4,"arm_r":4,"body":4,"comp":3,"id":42,"legs":4,"pack":3,"pilot":58,"pod_l":5,"pod_r":5,"wpn_l":6,"wpn_r":6},{"arm_l":4,"arm_r":4,"body":4,"comp":5,"id":43,"legs":4,"pack":5,"pilot":7,"pod_l":5,"pod_r":5,"wpn_l":5,"wpn_r":5},{"arm_l":4,"arm_r":4,"body":4,"comp":2,"id":44,"legs":4,"pack":2,"pilot":25,"pod_l":4,"pod_r":4,"wpn_l":6,"wpn_r":6},{"arm_l":5,"arm_r":5,"body":5,"comp":5,"id":45,"legs":5,"pack":2,"pilot":26,"pod_l":5,"pod_r":5,"wpn_l":1,"wpn_r":1},{"arm_l":5,"arm_r":5,"body":5,"comp":1,"id":46,"legs":5,"pack":3,"pilot":8,"pod_l":5,"pod_r":5,"wpn_l":4,"wpn_r":4},{"arm_l":1,"arm_r":1,"body":1,"comp":1,"id":47,"legs":1,"pack":3,"pilot":55,"pod_l":4,"pod_r":4,"wpn_l":2,"wpn_r":2},{"arm_l":4,"arm_r":4,"body":4,"comp":5,"id":48,"legs":4,"pack":3,"pilot":24,"pod_l":1,"pod_r":1,"wpn_l":2,"wpn_r":2},{"arm_l":2,"arm_r":2,"body":2,"comp":3,"id":49,"legs":2,"pack":3,"pilot":56,"pod_l":1,"pod_r":1,"wpn_l":5,"wpn_r":5},{"arm_l":5,"arm_r":5,"body":5,"comp":5,"id":50,"legs":5,"pack":5,"pilot":28,"pod_l":1,"pod_r":1,"wpn_l":3,"wpn_r":3},{"arm_l":5,"arm_r":5,"body":5,"comp":4,"id":51,"legs":5,"pack":5,"pilot":4,"pod_l":2,"pod_r":2,"wpn_l":8,"wpn_r":8},{"arm_l":5,"arm_r":5,"body":5,"comp":2,"id":52,"legs":5,"pack":4,"pilot":16,"pod_l":4,"pod_r":4,"wpn_l":3,"wpn_r":3},{"arm_l":4,"arm_r":4,"body":4,"comp":3,"id":53,"legs":4,"pack":3,"pilot":42,"pod_l":1,"pod_r":1,"wpn_l":7,"wpn_r":7},{"arm_l":2,"arm_r":2,"body":2,"comp":4,"id":54,"legs":2,"pack":5,"pilot":30,"pod_l":5,"pod_r":5,"wpn_l":8,"wpn_r":8},{"arm_l":3,"arm_r":3,"body":3,"comp":3,"id":55,"legs":3,"pack":2,"pilot":51,"pod_l":5,"pod_r":5,"wpn_l":6,"wpn_r":6},{"arm_l":4,"arm_r":4,"body":4,"comp":2,"id":56,"legs":4,"pack":3,"pilot":59,"pod_l":1,"pod_r":1,"wpn_l":2,"wpn_r":2},{"arm_l":5,"arm_r":5,"body":5,"comp":1,"id":57,"legs":5,"pack":5,"pilot":50,"pod_l":2,"pod_r":2,"wpn_l":6,"wpn_r":6},{"arm_l":2,"arm_r":2,"body":2,"comp":3,"id":58,"legs":2,"pack":3,"pilot":20,"pod_l":1,"pod_r":1,"wpn_l":3,"wpn_r":3},{"arm_l":5,"arm_r":5,"body":5,"comp":1,"id":59,"legs":5,"pack":3,"pilot":19,"pod_l":4,"pod_r":4,"wpn_l":2,"wpn_r":2},{"arm_l":3,"arm_r":3,"body":3,"comp":3,"id":60,"legs":3,"pack":1,"pilot":37,"pod_l":5,"pod_r":5,"wpn_l":4,"wpn_r":4},{"arm_l":2,"arm_r":2,"body":2,"comp":5,"id":61,"legs":2,"pack":5,"pilot":34,"pod_l":1,"pod_r":1,"wpn_l":8,"wpn_r":8},{"arm_l":2,"arm_r":2,"body":2,"comp":4,"id":62,"legs":2,"pack":3,"pilot":64,"pod_l":3,"pod_r":3,"wpn_l":1,"wpn_r":1},{"arm_l":2,"arm_r":2,"body":2,"comp":2,"id":63,"legs":2,"pack":1,"pilot":44,"pod_l":5,"pod_r":5,"wpn_l":6,"wpn_r":6},{"arm_l":1,"arm_r":1,"body":1,"comp":4,"id":64,"legs":1,"pack":3,"pilot":19,"pod_l":1,"pod_r":1,"wpn_l":2,"wpn_r":2},{"arm_l":5,"arm_r":5,"body":5,"comp":4,"id":65,"legs":5,"pack":5,"pilot":39,"pod_l":5,"pod_r":5,"wpn_l":1,"wpn_r":1},{"arm_l":5,"arm_r":5,"body":5,"comp":1,"id":66,"legs":5,"pack":5,"pilot":52,"pod_l":4,"pod_r":4,"wpn_l":6,"wpn_r":6},{"arm_l":4,"arm_r":4,"body":4,"comp":2,"id":67,"legs":4,"pack":5,"pilot":2,"pod_l":1,"pod_r":1,"wpn_l":4,"wpn_r":4},{"arm_l":5,"arm_r":5,"body":5,"comp":5,"id":68,"legs":5,"pack":4,"pilot":43,"pod_l":4,"pod_r":4,"wpn_l":2,"wpn_r":2},{"arm_l":4,"arm_r":4,"body":4,"comp":3,"id":69,"legs":4,"pack":3,"pilot":42,"pod_l":1,"pod_r":1,"wpn_l":5,"wpn_r":5},{"arm_l":5,"arm_r":5,"body":5,"comp":5,"id":70,"legs":5,"pack":2,"pilot":50,"pod_l":5,"pod_r":5,"wpn_l":2,"wpn_r":2},{"arm_l":4,"arm_r":4,"body":4,"comp":2,"id":71,"legs":4,"pack":2,"pilot":12,"pod_l":4,"pod_r":4,"wpn_l":5,"wpn_r":5},{"arm_l":1,"arm_r":1,"body":1,"comp":1,"id":72,"legs":1,"pack":4,"pilot":60,"pod_l":1,"pod_r":1,"wpn_l":8,"wpn_r":8},{"arm_l":3,"arm_r":3,"body":3,"comp":5,"id":73,"legs":3,"pack":3,"pilot":37,"pod_l":3,"pod_r":3,"wpn_l":1,"wpn_r":1},{"arm_l":2,"arm_r":2,"body":2,"comp":4,"id":74,"legs":2,"pack":1,"pilot":32,"pod_l":5,"pod_r":5,"wpn_l":5,"wpn_r":5},{"arm_l":3,"arm_r":3,"body":3,"comp":2,"id":75,"legs":3,"pack":3,"pilot":53,"pod_l":2,"pod_r":2,"wpn_l":2,"wpn_r":2},{"arm_l":4,"arm_r":4,"body":4,"comp":1,"id":76,"legs":4,"pack":5,"pilot":41,"pod_l":5,"pod_r":5,"wpn_l":4,"wpn_r":4},{"arm_l":3,"arm_r":3,"body":3,"comp":5,"id":77,"legs":3,"pack":4,"pilot":40,"pod_l":4,"pod_r":4,"wpn_l":8,"wpn_r":8},{"arm_l":4,"arm_r":4,"body":4,"comp":4,"id":78,"legs":4,"pack":4,"pilot":27,"pod_l":4,"pod_r":4,"wpn_l":7,"wpn_r":7},{"arm_l":5,"arm_r":5,"body":5,"comp":1,"id":79,"legs":5,"pack":2,"pilot":18,"pod_l":5,"pod_r":5,"wpn_l":7,"wpn_r":7},{"arm_l":4,"arm_r":4,"body":4,"comp":5,"id":80,"legs":4,"pack":5,"pilot":62,"pod_l":1,"pod_r":1,"wpn_l":4,"wpn_r":4},{"arm_l":2,"arm_r":2,"body":2,"comp":2,"id":81,"legs":2,"pack":4,"pilot":51,"pod_l":2,"pod_r":2,"wpn_l":3,"wpn_r":3},{"arm_l":2,"arm_r":2,"body":2,"comp":3,"id":82,"legs":2,"pack":3,"pilot":35,"pod_l":3,"pod_r":3,"wpn_l":5,"wpn_r":5},{"arm_l":3,"arm_r":3,"body":3,"comp":5,"id":83,"legs":3,"pack":4,"pilot":4,"pod_l":4,"pod_r":4,"wpn_l":4,"wpn_r":4},{"arm_l":3,"arm_r":3,"body":3,"comp":5,"id":84,"legs":3,"pack":4,"pilot":30,"pod_l":5,"pod_r":5,"wpn_l":6,"wpn_r":6},{"arm_l":4,"arm_r":4,"body":4,"comp":2,"id":85,"legs":4,"pack":3,"pilot":63,"pod_l":3,"pod_r":3,"wpn_l":5,"wpn_r":5},{"arm_l":4,"arm_r":4,"body":4,"comp":3,"id":86,"legs":4,"pack":4,"pilot":6,"pod_l":1,"pod_r":1,"wpn_l":5,"wpn_r":5},{"arm_l":2,"arm_r":2,"body":2,"comp":2,"id":87,"legs":2,"pack":5,"pilot":33,"pod_l":1,"pod_r":1,"wpn_l":7,"wpn_r":7},{"arm_l":2,"arm_r":2,"body":2,"comp":4,"id":88,"legs":2,"pack":3,"pilot":36,"pod_l":4,"pod_r":4,"wpn_l":2,"wpn_r":2},{"arm_l":5,"arm_r":5,"body":5,"comp":4,"id":89,"legs":5,"pack":3,"pilot":3,"pod_l":2,"pod_r":2,"wpn_l":5,"wpn_r":5},{"arm_l":4,"arm_r":4,"body":4,"comp":3,"id":90,"legs":4,"pack":3,"pilot":48,"pod_l":2,"pod_r":2,"wpn_l":8,"wpn_r":8},{"arm_l":1,"arm_r":1,"body":1,"comp":2,"id":91,"legs":1,"pack":4,"pilot":58,"pod_l":3,"pod_r":3,"wpn_l":5,"wpn_r":5},{"arm_l":5,"arm_r":5,"body":5,"comp":3,"id":92,"legs":5,"pack":1,"pilot":46,"pod_l":5,"pod_r":5,"wpn_l":8,"wpn_r":8},{"arm_l":1,"arm_r":1,"body":1,"comp":1,"id":93,"legs":1,"pack":3,"pilot":17,"pod_l":2,"pod_r":2,"wpn_l":3,"wpn_r":3},{"arm_l":2,"arm_r":2,"body":2,"comp":4,"id":94,"legs":2,"pack":5,"pilot":13,"pod_l":4,"pod_r":4,"wpn_l":5,"wpn_r":5},{"arm_l":5,"arm_r":5,"body":5,"comp":1,"id":95,"legs":5,"pack":2,"pilot":34,"pod_l":3,"pod_r":3,"wpn_l":6,"wpn_r":6},{"arm_l":4,"arm_r":4,"body":4,"comp":3,"id":96,"legs":4,"pack":5,"pilot":57,"pod_l":1,"pod_r":1,"wpn_l":3,"wpn_r":3},{"arm_l":1,"arm_r":1,"body":1,"comp":2,"id":97,"legs":1,"pack":2,"pilot":24,"pod_l":2,"pod_r":2,"wpn_l":6,"wpn_r":6},{"arm_l":5,"arm_r":5,"body":5,"comp":1,"id":98,"legs":5,"pack":3,"pilot":11,"pod_l":5,"pod_r":5,"wpn_l":8,"wpn_r":8},{"arm_l":4,"arm_r":4,"body":4,"comp":1,"id":99,"legs":4,"pack":2,"pilot":16,"pod_l":5,"pod_r":5,"wpn_l":3,"wpn_r":3},{"arm_l":3,"arm_r":3,"body":3,"comp":4,"id":100,"legs":3,"pack":5,"pilot":43,"pod_l":2,"pod_r":2,"wpn_l":4,"wpn_r":4},{"arm_l":2,"arm_r":2,"body":2,"comp":4,"id":101,"legs":2,"pack":1,"pilot":64,"pod_l":2,"pod_r":2,"wpn_l":4,"wpn_r":4},{"arm_l":4,"arm_r":4,"body":4,"comp":3,"id":102,"legs":4,"pack":5,"pilot":47,"pod_l":2,"pod_r":2,"wpn_l":1,"wpn_r":1},{"arm_l":1,"arm_r":1,"body":1,"comp":5,"id":103,"legs":1,"pack":2,"pilot":6,"pod_l":1,"pod_r":1,"wpn_l":7,"wpn_r":7},{"arm_l":4,"arm_r":4,"body":4,"comp":1,"id":104,"legs":4,"pack":4,"pilot":23,"pod_l":1,"pod_r":1,"wpn_l":2,"wpn_r":2},{"arm_l":1,"arm_r":1,"body":1,"comp":5,"id":105,"legs":1,"pack":2,"pilot":36,"pod_l":3,"pod_r":3,"wpn_l":8,"wpn_r":8},{"arm_l":4,"arm_r":4,"body":4,"comp":2,"id":106,"legs":4,"pack":3,"pilot":10,"pod_l":5,"pod_r":5,"wpn_l":7,"wpn_r":7},{"arm_l":4,"arm_r":4,"body":4,"comp":3,"id":107,"legs":4,"pack":1,"pilot":32,"pod_l":3,"pod_r":3,"wpn_l":6,"wpn_r":6},{"arm_l":3,"arm_r":3,"body":3,"comp":3,"id":108,"legs":3,"pack":1,"pilot":62,"pod_l":4,"pod_r":4,"wpn_l":8,"wpn_r":8},{"arm_l":5,"arm_r":5,"body":5,"comp":1,"id":109,"legs":5,"pack":1,"pilot":12,"pod_l":3,"pod_r":3,"wpn_l":6,"wpn_r":6},{"arm_l":5,"arm_r":5,"body":5,"comp":4,"id":110,"legs":5,"pack":5,"pilot":38,"pod_l":1,"pod_r":1,"wpn_l":3,"wpn_r":3},{"arm_l":5,"arm_r":5,"body":5,"comp":4,"id":111,"legs":5,"pack":5,"pilot":13,"pod_l":5,"pod_r":5,"wpn_l":1,"wpn_r":1},{"arm_l":5,"arm_r":5,"body":5,"comp":4,"id":112,"legs":5,"pack":5,"pilot":8,"pod_l":4,"pod_r":4,"wpn_l":7,"wpn_r":7},{"arm_l":2,"arm_r":2,"body":2,"comp":3,"id":113,"legs":2,"pack":5,"pilot":42,"pod_l":3,"pod_r":3,"wpn_l":8,"wpn_r":8},{"arm_l":4,"arm_r":4,"body":4,"comp":4,"id":114,"legs":4,"pack":2,"pilot":22,"pod_l":2,"pod_r":2,"wpn_l":6,"wpn_r":6},{"arm_l":1,"arm_r":1,"body":1,"comp":5,"id":115,"legs":1,"pack":5,"pilot":39,"pod_l":2,"pod_r":2,"wpn_l":1,"wpn_r":1},{"arm_l":3,"arm_r":3,"body":3,"comp":1,"id":116,"legs":3,"pack":2,"pilot":26,"pod_l":1,"pod_r":1,"wpn_l":4,"wpn_r":4},{"arm_l":3,"arm_r":3,"body":3,"comp":3,"id":117,"legs":3,"pack":3,"pilot":40,"pod_l":4,"pod_r":4,"wpn_l":5,"wpn_r":5},{"arm_l":4,"arm_r":4,"body":4,"comp":5,"id":118,"legs":4,"pack":3,"pilot":51,"pod_l":5,"pod_r":5,"wpn_l":6,"wpn_r":6},{"arm_l":5,"arm_r":5,"body":5,"comp":2,"id":119,"legs":5,"pack":5,"pilot":61,"pod_l":5,"pod_r":5,"wpn_l":7,"wpn_r":7},{"arm_l":1,"arm_r":1,"body":1,"comp":3,"id":120,"legs":1,"pack":4,"pilot":49,"pod_l":4,"pod_r":4,"wpn_l":2,"wpn_r":2},{"arm_l":3,"arm_r":3,"body":3,"comp":5,"id":121,"legs":3,"pack":1,"pilot":9,"pod_l":2,"pod_r":2,"wpn_l":2,"wpn_r":2},{"arm_l":2,"arm_r":2,"body":2,"comp":5,"id":122,"legs":2,"pack":3,"pilot":4,"pod_l":3,"pod_r":3,"wpn_l":4,"wpn_r":4},{"arm_l":5,"arm_r":5,"body":5,"comp":4,"id":123,"legs":5,"pack":3,"pilot":41,"pod_l":2,"pod_r":2,"wpn_l":2,"wpn_r":2},{"arm_l":1,"arm_r":1,"body":1,"comp":5,"id":124,"legs":1,"pack":2,"pilot":1,"pod_l":3,"pod_r":3,"wpn_l":6,"wpn_r":6},{"arm_l":5,"arm_r":5,"body":5,"comp":1,"id":125,"legs":5,"pack":5,"pilot":59,"pod_l":2,"pod_r":2,"wpn_l":8,"wpn_r":8},{"arm_l":1,"arm_r":1,"body":1,"comp":4,"id":126,"legs":1,"pack":2,"pilot":27,"pod_l":1,"pod_r":1,"wpn_l":5,"wpn_r":5},{"arm_l":2,"arm_r":2,"body":2,"comp":2,"id":127,"legs":2,"pack":4,"pilot":53,"pod_l":5,"pod_r":5,"wpn_l":5,"wpn_r":5}]